kiara_modules/network_analysis/__init__.py
kiara_modules/network_analysis/defaults.py
kiara_modules/network_analysis/metadata_models.py
kiara_modules/network_analysis/py.typed
kiara_modules/network_analysis/utils.py
kiara_modules/network_analysis/value_types.py
kiara_modules/network_analysis/network_data/__init__.py
kiara_modules/network_analysis/network_data/find/__init__.py
kiara_modules/network_analysis/pipelines/.gitkeep
kiara_modules/network_analysis/pipelines/__init__.py
kiara_modules/network_analysis/resources/.gitkeep
kiara_modules/network_analysis/resources/templates/network_data_schama.sql.j2
kiara_modules.network_analysis-0.3.1.dist-info/LICENSE
kiara_modules.network_analysis-0.3.1.dist-info/METADATA
kiara_modules.network_analysis-0.3.1.dist-info/WHEEL
kiara_modules.network_analysis-0.3.1.dist-info/entry_points.txt
kiara_modules.network_analysis-0.3.1.dist-info/top_level.txt
kiara_modules.network_analysis-0.3.1.dist-info/RECORD
