Metadata-Version: 2.1
Name: kiara-modules.network-analysis
Version: 0.3.1
Summary: A set of modules (and pipelines) for Kiara.
Home-page: https://github.com/DHARPA-project/kiara_modules.network_analysis
Author: Lena Jaskov
Author-email: helena.jaskov@uni.lu
License: MPL-2.0
Platform: any
Classifier: Development Status :: 3 - Alpha
Classifier: License :: OSI Approved :: Mozilla Public License 2.0 (MPL 2.0)
Classifier: Programming Language :: Python
Classifier: Programming Language :: Python :: 3
Classifier: Programming Language :: Python :: 3 :: Only
Classifier: Programming Language :: Python :: 3.8
Classifier: Programming Language :: Python :: 3.9
Requires-Python: >=3.8
License-File: LICENSE
Requires-Dist: kiara (>=0.3.3)
Requires-Dist: kiara-modules.core (>=0.3.5)
Provides-Extra: all
Requires-Dist: kiara[all] ; extra == 'all'
Provides-Extra: all_dev
Requires-Dist: types-python-dateutil ; extra == 'all_dev'
Requires-Dist: mkdocs-material (<8.0.0,>=7.1.0) ; extra == 'all_dev'
Requires-Dist: pre-commit (>=2.9.3) ; extra == 'all_dev'
Requires-Dist: mypy (>=0.800) ; extra == 'all_dev'
Requires-Dist: kiara[all] ; extra == 'all_dev'
Requires-Dist: ipython ; extra == 'all_dev'
Requires-Dist: mknotebooks (>=0.7.0) ; extra == 'all_dev'
Requires-Dist: setup-cfg-fmt (>=1.16.0) ; extra == 'all_dev'
Requires-Dist: mike (>=1.0.1) ; extra == 'all_dev'
Requires-Dist: watchgod (>=0.6) ; extra == 'all_dev'
Requires-Dist: pytest (>=6.2.2) ; extra == 'all_dev'
Requires-Dist: mkdocstrings (<0.16.0,>=0.15.2) ; extra == 'all_dev'
Requires-Dist: wheel ; extra == 'all_dev'
Requires-Dist: black ; extra == 'all_dev'
Requires-Dist: pip-licenses (>=3.3.0) ; extra == 'all_dev'
Requires-Dist: cruft (>=2.6.0) ; extra == 'all_dev'
Requires-Dist: types-pkg-resources ; extra == 'all_dev'
Requires-Dist: pytest-cov (>=2.11.1) ; extra == 'all_dev'
Requires-Dist: tox (>=3.21.2) ; extra == 'all_dev'
Requires-Dist: mkdocs-macros-plugin (<0.6.0,>=0.5.0) ; extra == 'all_dev'
Requires-Dist: icecream (>=2.1.0) ; extra == 'all_dev'
Requires-Dist: mkdocs-awesome-pages-plugin (>=2.5.0) ; extra == 'all_dev'
Requires-Dist: coveralls (>=3.2.0) ; extra == 'all_dev'
Requires-Dist: pp-ez (>=0.2.0) ; extra == 'all_dev'
Requires-Dist: flake8 (>=3.8.4) ; extra == 'all_dev'
Requires-Dist: mkdocs-gen-files (>=0.3.1) ; (python_version >= "3.7") and extra == 'all_dev'
Provides-Extra: cli
Requires-Dist: kiara[all] ; extra == 'cli'
Provides-Extra: dev_all
Requires-Dist: types-python-dateutil ; extra == 'dev_all'
Requires-Dist: mkdocs-material (<8.0.0,>=7.1.0) ; extra == 'dev_all'
Requires-Dist: pre-commit (>=2.9.3) ; extra == 'dev_all'
Requires-Dist: mypy (>=0.800) ; extra == 'dev_all'
Requires-Dist: kiara[all] ; extra == 'dev_all'
Requires-Dist: ipython ; extra == 'dev_all'
Requires-Dist: mknotebooks (>=0.7.0) ; extra == 'dev_all'
Requires-Dist: setup-cfg-fmt (>=1.16.0) ; extra == 'dev_all'
Requires-Dist: mike (>=1.0.1) ; extra == 'dev_all'
Requires-Dist: watchgod (>=0.6) ; extra == 'dev_all'
Requires-Dist: pytest (>=6.2.2) ; extra == 'dev_all'
Requires-Dist: mkdocstrings (<0.16.0,>=0.15.2) ; extra == 'dev_all'
Requires-Dist: wheel ; extra == 'dev_all'
Requires-Dist: black ; extra == 'dev_all'
Requires-Dist: pip-licenses (>=3.3.0) ; extra == 'dev_all'
Requires-Dist: cruft (>=2.6.0) ; extra == 'dev_all'
Requires-Dist: types-pkg-resources ; extra == 'dev_all'
Requires-Dist: pytest-cov (>=2.11.1) ; extra == 'dev_all'
Requires-Dist: tox (>=3.21.2) ; extra == 'dev_all'
Requires-Dist: mkdocs-macros-plugin (<0.6.0,>=0.5.0) ; extra == 'dev_all'
Requires-Dist: icecream (>=2.1.0) ; extra == 'dev_all'
Requires-Dist: mkdocs-awesome-pages-plugin (>=2.5.0) ; extra == 'dev_all'
Requires-Dist: coveralls (>=3.2.0) ; extra == 'dev_all'
Requires-Dist: pp-ez (>=0.2.0) ; extra == 'dev_all'
Requires-Dist: flake8 (>=3.8.4) ; extra == 'dev_all'
Requires-Dist: mkdocs-gen-files (>=0.3.1) ; (python_version >= "3.7") and extra == 'dev_all'
Provides-Extra: dev_documentation
Requires-Dist: icecream (>=2.1.0) ; extra == 'dev_documentation'
Requires-Dist: mike (>=1.0.1) ; extra == 'dev_documentation'
Requires-Dist: mkdocs-awesome-pages-plugin (>=2.5.0) ; extra == 'dev_documentation'
Requires-Dist: mkdocs-macros-plugin (<0.6.0,>=0.5.0) ; extra == 'dev_documentation'
Requires-Dist: mkdocs-material (<8.0.0,>=7.1.0) ; extra == 'dev_documentation'
Requires-Dist: mkdocstrings (<0.16.0,>=0.15.2) ; extra == 'dev_documentation'
Requires-Dist: mknotebooks (>=0.7.0) ; extra == 'dev_documentation'
Requires-Dist: mkdocs-gen-files (>=0.3.1) ; (python_version >= "3.7") and extra == 'dev_documentation'
Provides-Extra: dev_testing
Requires-Dist: coveralls (>=3.2.0) ; extra == 'dev_testing'
Requires-Dist: flake8 (>=3.8.4) ; extra == 'dev_testing'
Requires-Dist: mypy (>=0.800) ; extra == 'dev_testing'
Requires-Dist: pytest (>=6.2.2) ; extra == 'dev_testing'
Requires-Dist: pytest-cov (>=2.11.1) ; extra == 'dev_testing'
Requires-Dist: tox (>=3.21.2) ; extra == 'dev_testing'
Requires-Dist: types-pkg-resources ; extra == 'dev_testing'
Requires-Dist: types-python-dateutil ; extra == 'dev_testing'
Provides-Extra: dev_utils
Requires-Dist: black ; extra == 'dev_utils'
Requires-Dist: cruft (>=2.6.0) ; extra == 'dev_utils'
Requires-Dist: flake8 (>=3.8.4) ; extra == 'dev_utils'
Requires-Dist: ipython ; extra == 'dev_utils'
Requires-Dist: pip-licenses (>=3.3.0) ; extra == 'dev_utils'
Requires-Dist: pp-ez (>=0.2.0) ; extra == 'dev_utils'
Requires-Dist: pre-commit (>=2.9.3) ; extra == 'dev_utils'
Requires-Dist: setup-cfg-fmt (>=1.16.0) ; extra == 'dev_utils'
Requires-Dist: watchgod (>=0.6) ; extra == 'dev_utils'
Requires-Dist: wheel ; extra == 'dev_utils'
